{
    "boxShadow": "{{appsmith.theme.boxShadow.appBoxShadow}}",
    "borderColor": "#E0DEDE",
    "iconSVG": "/static/media/icon.46adf7030d667f0ad9002aa31f997573.svg",
    "onSubmit": "{{deleteBooking.run().then(() => {\n  getYourBuildingBookings.run();\n});}}",
    "topRow": 4,
    "type": "JSON_FORM_WIDGET",
    "animateLoading": true,
    "leftColumn": 0,
    "dynamicBindingPathList": [
        {"key": "borderRadius"},
        {"key": "boxShadow"},
        {"key": "submitButtonStyles.buttonColor"},
        {"key": "submitButtonStyles.borderRadius"},
        {"key": "resetButtonStyles.buttonColor"},
        {"key": "resetButtonStyles.borderRadius"},
        {"key": "sourceData"},
        {"key": "schema.__root_schema__.children.BookingId.defaultValue"},
        {"key": "schema.__root_schema__.children.BookingId.accentColor"},
        {"key": "schema.__root_schema__.children.BookingId.borderRadius"},
        {"key": "schema.__root_schema__.defaultValue"},
        {"key": "schema.__root_schema__.borderRadius"},
        {"key": "schema.__root_schema__.cellBorderRadius"}
    ],
    "showReset": false,
    "flexVerticalAlignment": "start",
    "dynamicHeight": "AUTO_HEIGHT",
    "autoGenerateForm": true,
    "resetButtonStyles": {
        "boxShadow": "none",
        "borderRadius": "{{appsmith.theme.borderRadius.appBorderRadius}}",
        "buttonColor": "{{appsmith.theme.colors.primaryColor}}",
        "buttonVariant": "SECONDARY"
    },
    "isVisible": true,
    "version": 1,
    "tags": [
        "Suggested",
        "Layout"
    ],
    "isLoading": false,
    "submitButtonLabel": "Delete",
    "childStylesheet": {
        "CHECKBOX": {
            "borderRadius": "{{appsmith.theme.borderRadius.appBorderRadius}}",
            "accentColor": "{{appsmith.theme.colors.primaryColor}}"
        },
        "ARRAY": {
            "boxShadow": "none",
            "borderRadius": "{{appsmith.theme.borderRadius.appBorderRadius}}",
            "accentColor": "{{appsmith.theme.colors.primaryColor}}",
            "cellBorderRadius": "{{appsmith.theme.borderRadius.appBorderRadius}}",
            "cellBoxShadow": "none"
        },
        "CURRENCY_INPUT": {
            "boxShadow": "none",
            "borderRadius": "{{appsmith.theme.borderRadius.appBorderRadius}}",
            "accentColor": "{{appsmith.theme.colors.primaryColor}}"
        },
        "DATEPICKER": {
            "boxShadow": "none",
            "borderRadius": "{{appsmith.theme.borderRadius.appBorderRadius}}",
            "accentColor": "{{appsmith.theme.colors.primaryColor}}"
        },
        "PHONE_NUMBER_INPUT": {
            "boxShadow": "none",
            "borderRadius": "{{appsmith.theme.borderRadius.appBorderRadius}}",
            "accentColor": "{{appsmith.theme.colors.primaryColor}}"
        },
        "OBJECT": {
            "boxShadow": "none",
            "borderRadius": "{{appsmith.theme.borderRadius.appBorderRadius}}",
            "cellBorderRadius": "{{appsmith.theme.borderRadius.appBorderRadius}}",
            "cellBoxShadow": "none"
        },
        "MULTISELECT": {
            "boxShadow": "none",
            "borderRadius": "{{appsmith.theme.borderRadius.appBorderRadius}}",
            "accentColor": "{{appsmith.theme.colors.primaryColor}}"
        },
        "SELECT": {
            "boxShadow": "none",
            "borderRadius": "{{appsmith.theme.borderRadius.appBorderRadius}}",
            "accentColor": "{{appsmith.theme.colors.primaryColor}}"
        },
        "NUMBER_INPUT": {
            "boxShadow": "none",
            "borderRadius": "{{appsmith.theme.borderRadius.appBorderRadius}}",
            "accentColor": "{{appsmith.theme.colors.primaryColor}}"
        },
        "PASSWORD_INPUT": {
            "boxShadow": "none",
            "borderRadius": "{{appsmith.theme.borderRadius.appBorderRadius}}",
            "accentColor": "{{appsmith.theme.colors.primaryColor}}"
        },
        "EMAIL_INPUT": {
            "boxShadow": "none",
            "borderRadius": "{{appsmith.theme.borderRadius.appBorderRadius}}",
            "accentColor": "{{appsmith.theme.colors.primaryColor}}"
        },
        "RADIO_GROUP": {
            "boxShadow": "none",
            "accentColor": "{{appsmith.theme.colors.primaryColor}}"
        },
        "SWITCH": {
            "boxShadow": "none",
            "accentColor": "{{appsmith.theme.colors.primaryColor}}"
        },
        "TEXT_INPUT": {
            "boxShadow": "none",
            "borderRadius": "{{appsmith.theme.borderRadius.appBorderRadius}}",
            "accentColor": "{{appsmith.theme.colors.primaryColor}}"
        },
        "MULTILINE_TEXT_INPUT": {
            "boxShadow": "none",
            "borderRadius": "{{appsmith.theme.borderRadius.appBorderRadius}}",
            "accentColor": "{{appsmith.theme.colors.primaryColor}}"
        }
    },
    "disabledWhenInvalid": true,
    "borderRadius": "{{appsmith.theme.borderRadius.appBorderRadius}}",
    "originalBottomRow": 32,
    "useSourceData": false,
    "schema": {"__root_schema__": {
        "labelTextSize": "0.875rem",
        "identifier": "__root_schema__",
        "boxShadow": "none",
        "isRequired": false,
        "isCustomField": false,
        "defaultValue": "{{((sourceData, formData, fieldState) => (sourceData))(JSONForm1.sourceData, JSONForm1.formData, JSONForm1.fieldState)}}",
        "dataType": "object",
        "cellBorderRadius": "{{((sourceData, formData, fieldState) => ((appsmith.theme.borderRadius.appBorderRadius)))(JSONForm1.sourceData, JSONForm1.formData, JSONForm1.fieldState)}}",
        "accessor": "__root_schema__",
        "isVisible": true,
        "label": "",
        "originalIdentifier": "__root_schema__",
        "borderRadius": "{{((sourceData, formData, fieldState) => ((appsmith.theme.borderRadius.appBorderRadius)))(JSONForm1.sourceData, JSONForm1.formData, JSONForm1.fieldState)}}",
        "children": {"BookingId": {
            "labelTextSize": "0.875rem",
            "identifier": "BookingId",
            "boxShadow": "none",
            "isRequired": false,
            "isCustomField": false,
            "defaultValue": "{{((sourceData, formData, fieldState) => (sourceData.BookingId))(JSONForm1.sourceData, JSONForm1.formData, JSONForm1.fieldState)}}",
            "accentColor": "{{((sourceData, formData, fieldState) => ((appsmith.theme.colors.primaryColor)))(JSONForm1.sourceData, JSONForm1.formData, JSONForm1.fieldState)}}",
            "dataType": "number",
            "accessor": "BookingId",
            "isVisible": true,
            "label": "Booking Id",
            "originalIdentifier": "BookingId",
            "borderRadius": "{{((sourceData, formData, fieldState) => ((appsmith.theme.borderRadius.appBorderRadius)))(JSONForm1.sourceData, JSONForm1.formData, JSONForm1.fieldState)}}",
            "children": {},
            "isSpellCheck": false,
            "iconAlign": "left",
            "position": 0,
            "isDisabled": true,
            "sourceData": 251512665,
            "fieldType": "Number Input"
        }},
        "position": -1,
        "isDisabled": false,
        "sourceData": {"BookingId": 251512665},
        "cellBoxShadow": "none",
        "fieldType": "Object"
    }},
    "needsErrorInfo": false,
    "mobileBottomRow": 77,
    "widgetName": "JSONForm1",
    "submitButtonStyles": {
        "boxShadow": "none",
        "borderRadius": "{{appsmith.theme.borderRadius.appBorderRadius}}",
        "buttonColor": "{{appsmith.theme.colors.primaryColor}}",
        "buttonVariant": "PRIMARY"
    },
    "dynamicPropertyPathList": [],
    "displayName": "JSON Form",
    "bottomRow": 31,
    "fieldLimitExceeded": false,
    "parentRowSpace": 10,
    "title": "Form",
    "hideCard": false,
    "mobileRightColumn": 44,
    "parentColumnSpace": 6.56941756606102,
    "dynamicTriggerPathList": [{"key": "onSubmit"}],
    "borderWidth": "1",
    "sourceData": "{{Table1.selectedRow}}",
    "resetButtonLabel": "Reset",
    "key": "vj7w4pawj5",
    "backgroundColor": "#fff",
    "isDeprecated": false,
    "rightColumn": 64,
    "widgetId": "uqjn0e7wl8",
    "minWidth": 450,
    "parentId": "kew2mh7zuo",
    "renderMode": "CANVAS",
    "mobileTopRow": 36,
    "scrollContents": true,
    "responsiveBehavior": "fill",
    "fixedFooter": true,
    "originalTopRow": 5,
    "mobileLeftColumn": 19,
    "maxDynamicHeight": 9000,
    "minDynamicHeight": 4
}